reprozip_web.py
setup.py
reprozip_web.egg-info/PKG-INFO
reprozip_web.egg-info/SOURCES.txt
reprozip_web.egg-info/dependency_links.txt
reprozip_web.egg-info/top_level.txt