Metadata-Version: 1.0
Name: reprozip-web
Version: 0.0
Summary: Allows the ReproZip unpacker to record and replay data journalism websites packaged as .rpz files
Home-page: UNKNOWN
Author: UNKNOWN
Author-email: UNKNOWN
License: UNKNOWN
Platform: UNKNOWN
